[
  {
    "id": "rebekkah",
    "name": "Rebekkah H.",
    "source": "Google Review",
    "quote": "Communication, customer service and fair pricing stood out by a mile.",
    "context": "Kitchen renovation and home study joinery in Sydney."
  },
  {
    "id": "lisa",
    "name": "Lisa P.",
    "source": "Google Review",
    "quote": "Prompt and professional service, quality work, and super happy with the end result.",
    "context": "Custom kitchen project and installation experience"
  },
  {
    "id": "julie",
    "name": "Julie S.",
    "source": "Google Review",
    "quote": "Went above and beyond — words cannot express how happy I am with the way my kitchen looks.",
    "context": "Kitchen renovation result and finish quality"
  },
  {
    "id": "pascal",
    "name": "Pascal S.",
    "source": "Google Review",
    "quote": "From start to finish, their professionalism and craftsmanship were exceptional.",
    "context": "Full joinery project with strong communication and execution"
  },
  {
    "id": "oussama",
    "name": "Oussama A.",
    "source": "Google Review",
    "quote": "The quality of the wardrobes is outstanding, with meticulous attention to detail.",
    "context": "Custom wardrobe joinery project"
  },
  {
    "id": "chang",
    "name": "Chang T.",
    "source": "Google Review",
    "quote": "Highly professional, creative and detail-focused — the transformation was stunning.",
    "context": "Kitchen renovation and full project execution"
  },
  {
    "id": "sam",
    "name": "Sam H.",
    "source": "Google Review",
    "quote": "Extremely professional and approachable, did a fabulous job with great attention to detail.",
    "context": "Residential joinery project with strong finish quality"
  },
  {
    "id": "karim",
    "name": "Karim B.",
    "source": "Google Review",
    "quote": "Finished within the promised timeframe and reasonably priced — highly recommended.",
    "context": "Joinery project delivery and timing"
  }
]
